{
  "project_info": {
    "project_number": "594155142630",
    "project_id": "hello-3960e",
    "storage_bucket": "hello-3960e.appspot.com"
  },
  "client": [
    {
      "client_info": {
        "mobilesdk_app_id": "1:594155142630:android:a104759bb863a576e42a27",
        "android_client_info": {
          "package_name": "com.example.hello"
        }
      },
      "oauth_client": [
        {
          "client_id": "594155142630-kceqbbml5pt5lfledeel5nh2bgikc2r8.apps.googleusercontent.com",
          "client_type": 3
        }
      ],
      "api_key": [
        {
          "current_key": "AIzaSyD2Ll1dPNJMwDFPc_iVXX3jV1M6krdTr2Y"
        }
      ],
      "services": {
        "appinvite_service": {
          "other_platform_oauth_client": [
            {
              "client_id": "594155142630-kceqbbml5pt5lfledeel5nh2bgikc2r8.apps.googleusercontent.com",
              "client_type": 3
            }
          ]
        }
      }
    }
  ],
  "configuration_version": "1"
}